local_retro/Retrosynthesis.py
local_retro/__init__.py
local_retro/LocalTemplate/__init__.py
local_retro/LocalTemplate/template_decoder.py
local_retro/LocalTemplate/template_extract_utils.py
local_retro/LocalTemplate/template_extractor.py
local_retro/preprocessing/Extract_from_train_data.py
local_retro/preprocessing/Run_preprocessing.py
local_retro/preprocessing/__init__.py
local_retro/scripts/Decode_predictions.py
local_retro/scripts/Test.py
local_retro/scripts/Train.py
local_retro/scripts/__init__.py
local_retro/scripts/dataset.py
local_retro/scripts/get_edit.py
local_retro/scripts/model_utils.py
local_retro/scripts/models.py
local_retro/scripts/utils.py
syntheseus_local_retro-0.5.0.dist-info/LICENSE
syntheseus_local_retro-0.5.0.dist-info/METADATA
syntheseus_local_retro-0.5.0.dist-info/WHEEL
syntheseus_local_retro-0.5.0.dist-info/top_level.txt
syntheseus_local_retro-0.5.0.dist-info/RECORD
