Metadata-Version: 2.1
Name: syntheseus-local-retro
Version: 0.5.0
Summary: Fork of LocalRetro for use in the syntheseus library
License-File: LICENSE
Requires-Dist: dgllife
Requires-Dist: chardet
Requires-Dist: pandas <2.2
